parflowio/_pyParflowio.so
parflowio/__init__.py
parflowio/pyParflowio.py
parflowio/.dylibs/libparflowio_shared.dylib
parflowio-0.0.7.dist-info/RECORD
parflowio-0.0.7.dist-info/WHEEL
parflowio-0.0.7.dist-info/top_level.txt
parflowio-0.0.7.dist-info/METADATA
