Metadata-Version: 2.1
Name: parflowio
Version: 0.0.7
Summary: UNKNOWN
Home-page: https://github.com/hydroframe/parflowio
Author: arezaii
Author-email: "Parflow Dev Team" <parflow@parflow.io>
License: UNKNOWN
Platform: UNKNOWN
Requires-Dist: numpy (>1.6.1)
